{"swagger":"2.0","info":{"version":"1.0","title":"接口文档","contact":{}},"host":"localhost:8081","basePath":"/api","tags":[{"name":"auth-controller","x-order":"2147483647"},{"name":"profile-controller","x-order":"2147483647"}],"paths":{"/api/auth/login":{"post":{"tags":["auth-controller"],"summary":"login","operationId":"loginUsingPOST","consumes":["application/json"],"produces":["*/*"],"parameters":[{"in":"body","name":"loginRequest","description":"loginRequest","required":true,"schema":{"originalRef":"LoginRequest","$ref":"#/definitions/LoginRequest"}}],"responses":{"200":{"description":"OK","schema":{"originalRef":"Result«LoginUserVO»","$ref":"#/definitions/Result«LoginUserVO»"}},"201":{"description":"Created"},"401":{"description":"Unauthorized"},"403":{"description":"Forbidden"},"404":{"description":"Not Found"}},"responsesObject":{"200":{"description":"OK","schema":{"originalRef":"Result«LoginUserVO»","$ref":"#/definitions/Result«LoginUserVO»"}},"201":{"description":"Created"},"401":{"description":"Unauthorized"},"403":{"description":"Forbidden"},"404":{"description":"Not Found"}},"deprecated":false,"x-order":"2147483647"}},"/api/auth/logout":{"post":{"tags":["auth-controller"],"summary":"logout","operationId":"logoutUsingPOST","consumes":["application/json"],"produces":["*/*"],"responses":{"200":{"description":"OK","schema":{"originalRef":"Result«boolean»","$ref":"#/definitions/Result«boolean»"}},"201":{"description":"Created"},"401":{"description":"Unauthorized"},"403":{"description":"Forbidden"},"404":{"description":"Not Found"}},"responsesObject":{"200":{"description":"OK","schema":{"originalRef":"Result«boolean»","$ref":"#/definitions/Result«boolean»"}},"201":{"description":"Created"},"401":{"description":"Unauthorized"},"403":{"description":"Forbidden"},"404":{"description":"Not Found"}},"deprecated":false,"x-order":"2147483647"}},"/api/auth/me":{"get":{"tags":["auth-controller"],"summary":"getLoginUser","operationId":"getLoginUserUsingGET","produces":["*/*"],"responses":{"200":{"description":"OK","schema":{"originalRef":"Result«LoginUserVO»","$ref":"#/definitions/Result«LoginUserVO»"}},"401":{"description":"Unauthorized"},"403":{"description":"Forbidden"},"404":{"description":"Not Found"}},"responsesObject":{"200":{"description":"OK","schema":{"originalRef":"Result«LoginUserVO»","$ref":"#/definitions/Result«LoginUserVO»"}},"401":{"description":"Unauthorized"},"403":{"description":"Forbidden"},"404":{"description":"Not Found"}},"deprecated":false,"x-order":"2147483647"}},"/api/auth/ok":{"get":{"tags":["auth-controller"],"summary":"ok","operationId":"okUsingGET","produces":["*/*"],"responses":{"200":{"description":"OK","schema":{"originalRef":"Result«string»","$ref":"#/definitions/Result«string»"}},"401":{"description":"Unauthorized"},"403":{"description":"Forbidden"},"404":{"description":"Not Found"}},"responsesObject":{"200":{"description":"OK","schema":{"originalRef":"Result«string»","$ref":"#/definitions/Result«string»"}},"401":{"description":"Unauthorized"},"403":{"description":"Forbidden"},"404":{"description":"Not Found"}},"deprecated":false,"x-order":"2147483647"}},"/api/auth/password/reset":{"post":{"tags":["auth-controller"],"summary":"resetPassword","operationId":"resetPasswordUsingPOST","consumes":["application/json"],"produces":["*/*"],"parameters":[{"in":"body","name":"passwordResetRequest","description":"passwordResetRequest","required":true,"schema":{"originalRef":"PasswordResetRequest","$ref":"#/definitions/PasswordResetRequest"}}],"responses":{"200":{"description":"OK","schema":{"originalRef":"Result«boolean»","$ref":"#/definitions/Result«boolean»"}},"201":{"description":"Created"},"401":{"description":"Unauthorized"},"403":{"description":"Forbidden"},"404":{"description":"Not Found"}},"responsesObject":{"200":{"description":"OK","schema":{"originalRef":"Result«boolean»","$ref":"#/definitions/Result«boolean»"}},"201":{"description":"Created"},"401":{"description":"Unauthorized"},"403":{"description":"Forbidden"},"404":{"description":"Not Found"}},"deprecated":false,"x-order":"2147483647"}},"/api/auth/register":{"post":{"tags":["auth-controller"],"summary":"register","operationId":"registerUsingPOST","consumes":["application/json"],"produces":["*/*"],"parameters":[{"in":"body","name":"registerRequest","description":"registerRequest","required":true,"schema":{"originalRef":"RegisterRequest","$ref":"#/definitions/RegisterRequest"}}],"responses":{"200":{"description":"OK","schema":{"originalRef":"Result«long»","$ref":"#/definitions/Result«long»"}},"201":{"description":"Created"},"401":{"description":"Unauthorized"},"403":{"description":"Forbidden"},"404":{"description":"Not Found"}},"responsesObject":{"200":{"description":"OK","schema":{"originalRef":"Result«long»","$ref":"#/definitions/Result«long»"}},"201":{"description":"Created"},"401":{"description":"Unauthorized"},"403":{"description":"Forbidden"},"404":{"description":"Not Found"}},"deprecated":false,"x-order":"2147483647"}},"/api/auth/send-code":{"post":{"tags":["auth-controller"],"summary":"sendCode","operationId":"sendCodeUsingPOST","consumes":["application/json"],"produces":["*/*"],"parameters":[{"in":"body","name":"request","description":"request","required":true,"schema":{"originalRef":"SendCodeRequest","$ref":"#/definitions/SendCodeRequest"}}],"responses":{"200":{"description":"OK","schema":{"originalRef":"Result«SendCodeResponse»","$ref":"#/definitions/Result«SendCodeResponse»"}},"201":{"description":"Created"},"401":{"description":"Unauthorized"},"403":{"description":"Forbidden"},"404":{"description":"Not Found"}},"responsesObject":{"200":{"description":"OK","schema":{"originalRef":"Result«SendCodeResponse»","$ref":"#/definitions/Result«SendCodeResponse»"}},"201":{"description":"Created"},"401":{"description":"Unauthorized"},"403":{"description":"Forbidden"},"404":{"description":"Not Found"}},"deprecated":false,"x-order":"2147483647"}},"/api/profile/avatar":{"put":{"tags":["profile-controller"],"summary":"uploadAvatar","operationId":"uploadAvatarUsingPUT","consumes":["multipart/form-data"],"produces":["*/*"],"parameters":[{"name":"file","in":"formData","description":"file","required":true,"type":"file"}],"responses":{"200":{"description":"OK","schema":{"originalRef":"Result«string»","$ref":"#/definitions/Result«string»"}},"201":{"description":"Created"},"401":{"description":"Unauthorized"},"403":{"description":"Forbidden"},"404":{"description":"Not Found"}},"responsesObject":{"200":{"description":"OK","schema":{"originalRef":"Result«string»","$ref":"#/definitions/Result«string»"}},"201":{"description":"Created"},"401":{"description":"Unauthorized"},"403":{"description":"Forbidden"},"404":{"description":"Not Found"}},"deprecated":false,"x-order":"2147483647"}},"/api/profile/info":{"get":{"tags":["profile-controller"],"summary":"getPrivateProfile","operationId":"getPrivateProfileUsingGET","produces":["*/*"],"responses":{"200":{"description":"OK","schema":{"originalRef":"Result«UserDetailVO»","$ref":"#/definitions/Result«UserDetailVO»"}},"401":{"description":"Unauthorized"},"403":{"description":"Forbidden"},"404":{"description":"Not Found"}},"responsesObject":{"200":{"description":"OK","schema":{"originalRef":"Result«UserDetailVO»","$ref":"#/definitions/Result«UserDetailVO»"}},"401":{"description":"Unauthorized"},"403":{"description":"Forbidden"},"404":{"description":"Not Found"}},"deprecated":false,"x-order":"2147483647"},"put":{"tags":["profile-controller"],"summary":"updateProfile","operationId":"updateProfileUsingPUT","consumes":["application/json"],"produces":["*/*"],"parameters":[{"in":"body","name":"updateProfileDTO","description":"updateProfileDTO","required":true,"schema":{"originalRef":"UpdateProfileDTO","$ref":"#/definitions/UpdateProfileDTO"}}],"responses":{"200":{"description":"OK","schema":{"originalRef":"Result«Void»","$ref":"#/definitions/Result«Void»"}},"201":{"description":"Created"},"401":{"description":"Unauthorized"},"403":{"description":"Forbidden"},"404":{"description":"Not Found"}},"responsesObject":{"200":{"description":"OK","schema":{"originalRef":"Result«Void»","$ref":"#/definitions/Result«Void»"}},"201":{"description":"Created"},"401":{"description":"Unauthorized"},"403":{"description":"Forbidden"},"404":{"description":"Not Found"}},"deprecated":false,"x-order":"2147483647"}},"/api/profile/{account}":{"get":{"tags":["profile-controller"],"summary":"getPublicProfile","operationId":"getPublicProfileUsingGET","produces":["*/*"],"parameters":[{"name":"account","in":"path","description":"account","required":true,"type":"string"}],"responses":{"200":{"description":"OK","schema":{"originalRef":"Result«UserVO»","$ref":"#/definitions/Result«UserVO»"}},"401":{"description":"Unauthorized"},"403":{"description":"Forbidden"},"404":{"description":"Not Found"}},"responsesObject":{"200":{"description":"OK","schema":{"originalRef":"Result«UserVO»","$ref":"#/definitions/Result«UserVO»"}},"401":{"description":"Unauthorized"},"403":{"description":"Forbidden"},"404":{"description":"Not Found"}},"deprecated":false,"x-order":"2147483647"}}},"definitions":{"LoginRequest":{"type":"object","properties":{"account":{"type":"string"},"code":{"type":"string"},"identifier":{"type":"string"},"identifierType":{"type":"string","enum":["PHONE","EMAIL"]},"password":{"type":"string"}},"title":"LoginRequest"},"LoginUserVO":{"type":"object","properties":{"account":{"type":"string"},"avatarUrl":{"type":"string"},"bio":{"type":"string"},"email":{"type":"string"},"lastLoginIp":{"type":"string"},"lastLoginTime":{"type":"string","format":"date-time"},"phone":{"type":"string"},"role":{"type":"string"},"school":{"type":"string"}},"title":"LoginUserVO"},"PasswordResetRequest":{"type":"object","properties":{"account":{"type":"string"},"code":{"type":"string"},"confirmPassword":{"type":"string"},"identifier":{"type":"string"},"identifierType":{"type":"string","enum":["PHONE","EMAIL"]},"newPassword":{"type":"string"}},"title":"PasswordResetRequest"},"RegisterRequest":{"type":"object","properties":{"account":{"type":"string"},"agreeTerms":{"type":"boolean"},"checkPassword":{"type":"string"},"code":{"type":"string"},"identifier":{"type":"string"},"identifierType":{"type":"string","enum":["PHONE","EMAIL"]},"password":{"type":"string"}},"title":"RegisterRequest"},"Result«LoginUserVO»":{"type":"object","properties":{"code":{"type":"integer","format":"int32"},"data":{"originalRef":"LoginUserVO","$ref":"#/definitions/LoginUserVO"},"msg":{"type":"string"}},"title":"Result«LoginUserVO»"},"Result«SendCodeResponse»":{"type":"object","properties":{"code":{"type":"integer","format":"int32"},"data":{"originalRef":"SendCodeResponse","$ref":"#/definitions/SendCodeResponse"},"msg":{"type":"string"}},"title":"Result«SendCodeResponse»"},"Result«UserDetailVO»":{"type":"object","properties":{"code":{"type":"integer","format":"int32"},"data":{"originalRef":"UserDetailVO","$ref":"#/definitions/UserDetailVO"},"msg":{"type":"string"}},"title":"Result«UserDetailVO»"},"Result«UserVO»":{"type":"object","properties":{"code":{"type":"integer","format":"int32"},"data":{"originalRef":"UserVO","$ref":"#/definitions/UserVO"},"msg":{"type":"string"}},"title":"Result«UserVO»"},"Result«Void»":{"type":"object","properties":{"code":{"type":"integer","format":"int32"},"msg":{"type":"string"}},"title":"Result«Void»"},"Result«boolean»":{"type":"object","properties":{"code":{"type":"integer","format":"int32"},"data":{"type":"boolean"},"msg":{"type":"string"}},"title":"Result«boolean»"},"Result«long»":{"type":"object","properties":{"code":{"type":"integer","format":"int32"},"data":{"type":"integer","format":"int64"},"msg":{"type":"string"}},"title":"Result«long»"},"Result«string»":{"type":"object","properties":{"code":{"type":"integer","format":"int32"},"data":{"type":"string"},"msg":{"type":"string"}},"title":"Result«string»"},"SendCodeRequest":{"type":"object","properties":{"account":{"type":"string"},"identifier":{"type":"string"},"identifierType":{"type":"string","enum":["PHONE","EMAIL"]},"scene":{"type":"string","enum":["REGISTER","LOGIN","RESET_PASSWORD"]}},"title":"SendCodeRequest"},"SendCodeResponse":{"type":"object","properties":{"expireSeconds":{"type":"integer","format":"int32"},"identifier":{"type":"string"},"scene":{"type":"string","enum":["REGISTER","LOGIN","RESET_PASSWORD"]}},"title":"SendCodeResponse"},"UpdateProfileDTO":{"type":"object","properties":{"account":{"type":"string"},"bio":{"type":"string"},"school":{"type":"string"}},"title":"UpdateProfileDTO"},"UserDetailVO":{"type":"object","properties":{"account":{"type":"string"},"avatarUrl":{"type":"string"},"bio":{"type":"string"},"createTime":{"type":"string","format":"date-time"},"email":{"type":"string"},"id":{"type":"integer","format":"int64"},"passwordHash":{"type":"string"},"phone":{"type":"string"},"role":{"type":"string"},"school":{"type":"string"},"status":{"type":"integer","format":"int32"}},"title":"UserDetailVO"},"UserVO":{"type":"object","properties":{"acceptedCount":{"type":"integer","format":"int32"},"account":{"type":"string"},"avatarUrl":{"type":"string"},"bio":{"type":"string"},"contestCount":{"type":"integer","format":"int32"},"courseCount":{"type":"integer","format":"int32"},"followerCount":{"type":"integer","format":"int32"},"followingCount":{"type":"integer","format":"int32"},"lastLoginIp":{"type":"string"},"lastLoginTime":{"type":"string","format":"date-time"},"pkCount":{"type":"integer","format":"int32"},"pkWinCount":{"type":"integer","format":"int32"},"rating":{"type":"integer","format":"int32"},"role":{"type":"string"},"school":{"type":"string"},"solvedCount":{"type":"integer","format":"int32"},"submitCount":{"type":"integer","format":"int32"}},"title":"UserVO"}},"x-openapi":{"x-markdownFiles":null,"x-setting":{"language":"zh-CN","enableSwaggerModels":true,"swaggerModelName":"Swagger Models","enableReloadCacheParameter":false,"enableAfterScript":true,"enableDocumentManage":true,"enableVersion":false,"enableRequestCache":true,"enableFilterMultipartApis":false,"enableFilterMultipartApiMethodType":"POST","enableHost":false,"enableHostText":"","enableDynamicParameter":false,"enableDebug":true,"enableFooter":true,"enableFooterCustom":false,"footerCustomContent":null,"enableSearch":true,"enableOpenApi":true,"enableHomeCustom":false,"homeCustomLocation":null,"enableGroup":true,"enableResponseCode":true}}}